{
  "version": "7",
  "dialect": "postgresql",
  "entries": [
    {
      "idx": 0,
      "version": "7",
      "when": 1769206657754,
      "tag": "20260123221737_safe_shotgun",
      "breakpoints": true
    },
    {
      "idx": 1,
      "version": "7",
      "when": 1769229245357,
      "tag": "20260124043405_cold_fantastic_four",
      "breakpoints": true
    },
    {
      "idx": 2,
      "version": "7",
      "when": 1769230224942,
      "tag": "20260124045024_fearless_dexter_bennett",
      "breakpoints": true
    }
  ]
}